README.rst
setup.py
expyrimenter/__init__.py
expyrimenter/config.py
expyrimenter/executor.py
expyrimenter/runnable.py
expyrimenter/shell.py
expyrimenter/ssh.py
expyrimenter.egg-info/PKG-INFO
expyrimenter.egg-info/SOURCES.txt
expyrimenter.egg-info/dependency_links.txt
expyrimenter.egg-info/requires.txt
expyrimenter.egg-info/top_level.txt
expyrimenter/apps/__init__.py
expyrimenter/apps/pushbullet.py
expyrimenter/clouds/__init__.py
expyrimenter/clouds/cloudstack/__init__.py
expyrimenter/clouds/cloudstack/api.py
expyrimenter/clouds/cloudstack/cloudstack.py
expyrimenter/clouds/cloudstack/statemonitor.py