Metadata-Version: 1.1
Name: expyrimenter
Version: 0.2.0
Summary: Python tool to ease and parallelize distributed system management tasks.
Home-page: https://github.com/cemsbr/expyrimenter
Author: Carlos Eduardo Moreira dos Santos
Author-email: cems@cemshost.com.br
License: GPLv3
Keywords: shell ssh cluster cloud install setup parallel
Platform: UNKNOWN
Classifier: Development Status :: 4 - Beta
Classifier: Intended Audience :: Developers
Classifier: Intended Audience :: System Administrators
Classifier: Topic :: System :: Installation/Setup
Classifier: Topic :: System :: Systems Administration
Classifier: License :: OSI Approved :: GNU General Public License v3 (GPLv3)
Classifier: Programming Language :: Python
Classifier: Programming Language :: Python :: 3
Classifier: Programming Language :: Python :: 3.2
Classifier: Programming Language :: Python :: 3.3
Classifier: Programming Language :: Python :: 3.4
